ipconflict/__init__.py
ipconflict/subnet.py
ipconflict-0.5.0.dist-info/LICENSE
ipconflict-0.5.0.dist-info/METADATA
ipconflict-0.5.0.dist-info/WHEEL
ipconflict-0.5.0.dist-info/entry_points.txt
ipconflict-0.5.0.dist-info/top_level.txt
ipconflict-0.5.0.dist-info/RECORD
